pixelator/__init__.py
pixelator/cli/__init__.py
pixelator/cli/main.py
pixelator/common/__init__.py
pixelator/common/annotate/__init__.py
pixelator/common/annotate/aggregates.py
pixelator/common/annotate/cell_calling.py
pixelator/common/annotate/constants.py
pixelator/common/config/__init__.py
pixelator/common/config/assay.py
pixelator/common/config/config_class.py
pixelator/common/config/panel.py
pixelator/common/config/utils.py
pixelator/common/exceptions.py
pixelator/common/graph/__init__.py
pixelator/common/graph/backends/__init__.py
pixelator/common/graph/backends/implementations/__init__.py
pixelator/common/graph/backends/implementations/_networkx.py
pixelator/common/graph/backends/protocol.py
pixelator/common/graph/graph.py
pixelator/common/graph/node_metrics.py
pixelator/common/marks.py
pixelator/common/report/json_encoder.py
pixelator/common/report/models/__init__.py
pixelator/common/report/models/summary_statistics.py
pixelator/common/statistics.py
pixelator/common/types.py
pixelator/common/utils/__init__.py
pixelator/common/utils/simplification.py
pixelator/common/utils/units.py
pixelator/mpx/__init__.py
pixelator/mpx/__main__.py
pixelator/mpx/amplicon/__init__.py
pixelator/mpx/amplicon/process.py
pixelator/mpx/amplicon/statistics.py
pixelator/mpx/analysis/__init__.py
pixelator/mpx/analysis/analysis_engine.py
pixelator/mpx/analysis/colocalization/__init__.py
pixelator/mpx/analysis/colocalization/estimate.py
pixelator/mpx/analysis/colocalization/prepare.py
pixelator/mpx/analysis/colocalization/statistics.py
pixelator/mpx/analysis/colocalization/types.py
pixelator/mpx/analysis/permute.py
pixelator/mpx/analysis/polarization/__init__.py
pixelator/mpx/analysis/polarization/types.py
pixelator/mpx/analysis/types.py
pixelator/mpx/annotate/__init__.py
pixelator/mpx/cli/__init__.py
pixelator/mpx/cli/adapterqc.py
pixelator/mpx/cli/amplicon.py
pixelator/mpx/cli/analysis.py
pixelator/mpx/cli/annotate.py
pixelator/mpx/cli/collapse.py
pixelator/mpx/cli/common.py
pixelgen_pixelator-0.22.0.dist-info/METADATA
pixelgen_pixelator-0.22.0.dist-info/WHEEL
pixelgen_pixelator-0.22.0.dist-info/entry_points.txt
pixelgen_pixelator-0.22.0.dist-info/licenses/LICENSE
pixelgen_pixelator-0.22.0.dist-info/RECORD
