Metadata-Version: 2.4
Name: pixelgen-pixelator
Version: 0.22.0
Summary: A command-line tool and library to process and analyze data generated from technologies from Pixelgen Technologies.
License: MIT
License-File: LICENSE
Keywords: protein,single-cell,molecular-pixelation,spatial,proteomics
Author: Pixelgen Technologies AB
Author-email: developers@pixelgen.com
Maintainer: Alvaro Martinez Barrio
Maintainer-email: alvaro.martinez.barrio@pixelgen.com
Requires-Python: >=3.10,<3.13
Classifier: Development Status :: 4 - Beta
Classifier: Intended Audience :: Developers
Classifier: Intended Audience :: Science/Research
Classifier: License :: OSI Approved :: MIT License
Classifier: Natural Language :: English
Classifier: Programming Language :: Python :: 3
Classifier: Programming Language :: Python :: 3.10
Classifier: Programming Language :: Python :: 3.11
Classifier: Programming Language :: Python :: 3.12
Classifier: Topic :: Scientific/Engineering :: Bio-Informatics
Requires-Dist: anndata (>=0.8.0)
Requires-Dist: annoy (<=1.17.0)
Requires-Dist: click (<8.3.0)
Requires-Dist: cssselect
Requires-Dist: cutadapt (>=4.2)
Requires-Dist: duckdb (>=1.4.1,<2.0.0)
Requires-Dist: faiss-cpu (>=1.10.0,<2.0.0)
Requires-Dist: fastparquet
Requires-Dist: fsspec
Requires-Dist: graspologic-native (>=1.2.4,<2.0.0)
Requires-Dist: importlib-resources (>=5.12.0,<6.0.0)
Requires-Dist: lxml
Requires-Dist: numba (>=0.56.4)
Requires-Dist: numpy (>=2.0.0,<3.0.0)
Requires-Dist: pandas (>=2.0.0,<3.0.0)
Requires-Dist: plotly
Requires-Dist: polars (>=1.0.0,<1.27.0)
Requires-Dist: pyarrow (>=14)
Requires-Dist: pydantic (>=2.0,<2.5)
Requires-Dist: pyfastx
Requires-Dist: ruamel-yaml (>=0.17.21,<0.18.0)
Requires-Dist: scanpy
Requires-Dist: scipy (>=1.0.0,<2.0.0)
Requires-Dist: semver (>=3.0.0,<4.0.0)
Requires-Dist: typing_extensions
Requires-Dist: umi_tools (>=1.1.4,<2.0.0)
Requires-Dist: xopen
Requires-Dist: xxhash
Requires-Dist: yapf
Requires-Dist: yappi
Requires-Dist: zstandard (>=0.23.0,<0.24.0)
Project-URL: Documentation, https://software.pixelgen.com
Project-URL: Homepage, https://github.com/PixelgenTechnologies/pixelator
Project-URL: Repository, https://github.com/PixelgenTechnologies/pixelator
